Workbook

Sheet Calculadora
B2: Calculadora de Costos
B3: Receta:
B5: Selecciona los ingredientes que neceesitas. | E5: Esto NO lo modifiques, es el resultado de lo que cuesta cada ingrediente.
B6: ⬇️ | E6: ⬇️ | F6: ⬇️
B7: Paso 1: Ingredientes | H7: Paso 2: Gastos y Ganancia | M7: {=SUM(C9:C18+C20)} -> 3040 | N7: =M7/30 -> 101.33333
B8: Ingredientes | C8: Cantidad | D8: Unidades | E8: Costo (por unidad) | F8: Precio | H8: Concepto | I8: Ejemplos | J8: Aumento | K8: Precio
B9: Chile morita | C9: 5 | D9: Gramos | E9: =IFERROR(_xlfn.XLOOKUP(B9,Ingredientes!B:B,Ingredientes!C:C),"") -> 200 | F9: =IF(E9="","",(ROUNDUP(C9*E9/IF(OR(D9="Kilo",D9="Litro"),1,IF(OR(D9="Gramos",D9="Mililitros"),1000,1)),0))) -> 1 | H9: Gastos Fijos | I9: Agua, Luz, Gas | J9: 0.2 | K9: =ROUNDUP(F33*(1+J9),0) -> 627
B10: Chile guajillo | C10: 20 | D10: Gramos | E10: =IFERROR(_xlfn.XLOOKUP(B10,Ingredientes!B:B,Ingredientes!C:C),"") -> 280 | F10: =IF(E10="","",(ROUNDUP(C10*E10/IF(OR(D10="Kilo",D10="Litro"),1,IF(OR(D10="Gramos",D10="Mililitros"),1000,1)),0))) -> 6 | H10: Ganancia | I10: Por tu trabajo | J10: 0.7 | K10: =ROUNDUP(K9*(1+J10),0) -> 1066
B11: Chile pasilla | C11: 25 | D11: Gramos | E11: =IFERROR(_xlfn.XLOOKUP(B11,Ingredientes!B:B,Ingredientes!C:C),"") -> 339 | F11: =IF(E11="","",(ROUNDUP(C11*E11/IF(OR(D11="Kilo",D11="Litro"),1,IF(OR(D11="Gramos",D11="Mililitros"),1000,1)),0))) -> 9
B12: Chile arbol | C12: 10 | D12: Gramos | E12: =IFERROR(_xlfn.XLOOKUP(B12,Ingredientes!B:B,Ingredientes!C:C),"") -> 108.5 | F12: =IF(E12="","",(ROUNDUP(C12*E12/IF(OR(D12="Kilo",D12="Litro"),1,IF(OR(D12="Gramos",D12="Mililitros"),1000,1)),0))) -> 2
B13: Ajo | C13: 160 | D13: Gramos | E13: =IFERROR(_xlfn.XLOOKUP(B13,Ingredientes!B:B,Ingredientes!C:C),"") -> 140 | F13: =IF(E13="","",(ROUNDUP(C13*E13/IF(OR(D13="Kilo",D13="Litro"),1,IF(OR(D13="Gramos",D13="Mililitros"),1000,1)),0))) -> 23 | H13: Paso 3: Unidades
B14: Nuez de la india | C14: 180 | D14: Gramos | E14: =IFERROR(_xlfn.XLOOKUP(B14,Ingredientes!B:B,Ingredientes!C:C),"") -> 339 | F14: =IF(E14="","",(ROUNDUP(C14*E14/IF(OR(D14="Kilo",D14="Litro"),1,IF(OR(D14="Gramos",D14="Mililitros"),1000,1)),0))) -> 62
B15: Pistache | C15: 180 | D15: Gramos | E15: =IFERROR(_xlfn.XLOOKUP(B15,Ingredientes!B:B,Ingredientes!C:C),"") -> 799 | F15: =IF(E15="","",(ROUNDUP(C15*E15/IF(OR(D15="Kilo",D15="Litro"),1,IF(OR(D15="Gramos",D15="Mililitros"),1000,1)),0))) -> 144 | H15: ¿Cuántos vas a hacer? | K15: Precio
B16: Arandano | C16: 185 | D16: Gramos | E16: =IFERROR(_xlfn.XLOOKUP(B16,Ingredientes!B:B,Ingredientes!C:C),"") -> 133 | F16: =IF(E16="","",(ROUNDUP(C16*E16/IF(OR(D16="Kilo",D16="Litro"),1,IF(OR(D16="Gramos",D16="Mililitros"),1000,1)),0))) -> 25 | H16: Unidades por receta | K16: 15 | L16: ⬅️ | M16: ¿Cuántos postres salen por receta?
B17: Nuez garapiñada | C17: 115 | D17: Gramos | E17: =IFERROR(_xlfn.XLOOKUP(B17,Ingredientes!B:B,Ingredientes!C:C),"") -> 450 | F17: =IF(E17="","",(ROUNDUP(C17*E17/IF(OR(D17="Kilo",D17="Litro"),1,IF(OR(D17="Gramos",D17="Mililitros"),1000,1)),0))) -> 52 | H17: Unidades por paquete | K17: 1 | L17: ⬅️ | M17: ¿Cuantos postres llevan cada bolsa o paquete?
B18: Avellana | C18: 160 | D18: Gramos | E18: =IFERROR(_xlfn.XLOOKUP(B18,Ingredientes!B:B,Ingredientes!C:C),"") -> 600 | F18: =IF(E18="","",(ROUNDUP(C18*E18/IF(OR(D18="Kilo",D18="Litro"),1,IF(OR(D18="Gramos",D18="Mililitros"),1000,1)),0))) -> 96 | H18: Precio por paquete | K18: =ROUNDUP($K$10/K16*K17,0) -> 72
B19: Aceite | C19: 2 | D19: Litro | E19: =IFERROR(_xlfn.XLOOKUP(B19,Ingredientes!B:B,Ingredientes!C:C),"") -> 37 | F19: =IF(E19="","",(ROUNDUP(C19*E19/IF(OR(D19="Kilo",D19="Litro"),1,IF(OR(D19="Gramos",D19="Mililitros"),1000,1)),0))) -> 74
B20: Ajonjoli | C20: 200 | D20: Gramos | E20: =IFERROR(_xlfn.XLOOKUP(B20,Ingredientes!B:B,Ingredientes!C:C),"") -> 130 | F20: =IF(E20="","",(ROUNDUP(C20*E20/IF(OR(D20="Kilo",D20="Litro"),1,IF(OR(D20="Gramos",D20="Mililitros"),1000,1)),0))) -> 26
B21: Vinagre blanco | C21: 50 | D21: Mililitros | E21: =IFERROR(_xlfn.XLOOKUP(B21,Ingredientes!B:B,Ingredientes!C:C),"") -> 18 | F21: =IF(E21="","",(ROUNDUP(C21*E21/IF(OR(D21="Kilo",D21="Litro"),1,IF(OR(D21="Gramos",D21="Mililitros"),1000,1)),0))) -> 1 | H21: Paso 4: Empaque
B22: Sal | C22: 7 | D22: Gramos | E22: =IFERROR(_xlfn.XLOOKUP(B22,Ingredientes!B:B,Ingredientes!C:C),"") -> 75 | F22: =IF(E22="","",(ROUNDUP(C22*E22/IF(OR(D22="Kilo",D22="Litro"),1,IF(OR(D22="Gramos",D22="Mililitros"),1000,1)),0))) -> 1
E23: =IFERROR(_xlfn.XLOOKUP(B23,Ingredientes!B:B,Ingredientes!C:C),"") -> 0 | F23: =IF(E23="","",(ROUNDUP(C23*E23/IF(OR(D23="Kilo",D23="Litro"),1,IF(OR(D23="Gramos",D23="Mililitros"),1000,1)),0))) -> 0 | H23: Finales | I23: Explicación | K23: Precio
E24: =IFERROR(_xlfn.XLOOKUP(B24,Ingredientes!B:B,Ingredientes!C:C),"") -> 0 | F24: =IF(E24="","",(ROUNDUP(C24*E24/IF(OR(D24="Kilo",D24="Litro"),1,IF(OR(D24="Gramos",D24="Mililitros"),1000,1)),0))) -> 0 | H24: Paquete | I24: Se obtiene del paso anterior | K24: =$K$18 -> 72
E25: =IFERROR(_xlfn.XLOOKUP(B25,Ingredientes!B:B,Ingredientes!C:C),"") -> 0 | F25: =IF(E25="","",(ROUNDUP(C25*E25/IF(OR(D25="Kilo",D25="Litro"),1,IF(OR(D25="Gramos",D25="Mililitros"),1000,1)),0))) -> 0 | H25: Frasco | K25: 33 | L25: ⬅️ | M25: Agrega los costos directos de cada paquete
E26: =IFERROR(_xlfn.XLOOKUP(B26,Ingredientes!B:B,Ingredientes!C:C),"") -> 0 | F26: =IF(E26="","",(ROUNDUP(C26*E26/IF(OR(D26="Kilo",D26="Litro"),1,IF(OR(D26="Gramos",D26="Mililitros"),1000,1)),0))) -> 0 | H26: Etiqueta | K26: 15
E27: =IFERROR(_xlfn.XLOOKUP(B27,Ingredientes!B:B,Ingredientes!C:C),"") -> 0 | F27: =IF(E27="","",(ROUNDUP(C27*E27/IF(OR(D27="Kilo",D27="Litro"),1,IF(OR(D27="Gramos",D27="Mililitros"),1000,1)),0))) -> 0
E28: =IFERROR(_xlfn.XLOOKUP(B28,Ingredientes!B:B,Ingredientes!C:C),"") -> 0 | F28: =IF(E28="","",(ROUNDUP(C28*E28/IF(OR(D28="Kilo",D28="Litro"),1,IF(OR(D28="Gramos",D28="Mililitros"),1000,1)),0))) -> 0 | L28: ⬅️ | M28: Puedes agregar más aquí abajo
E29: =IFERROR(_xlfn.XLOOKUP(B29,Ingredientes!B:B,Ingredientes!C:C),"") -> 0 | F29: =IF(E29="","",(ROUNDUP(C29*E29/IF(OR(D29="Kilo",D29="Litro"),1,IF(OR(D29="Gramos",D29="Mililitros"),1000,1)),0))) -> 0
E30: =IFERROR(_xlfn.XLOOKUP(B30,Ingredientes!B:B,Ingredientes!C:C),"") -> 0 | F30: =IF(E30="","",(ROUNDUP(C30*E30/IF(OR(D30="Kilo",D30="Litro"),1,IF(OR(D30="Gramos",D30="Mililitros"),1000,1)),0))) -> 0
E31: =IFERROR(_xlfn.XLOOKUP(B31,Ingredientes!B:B,Ingredientes!C:C),"") -> 0 | F31: =IF(E31="","",(ROUNDUP(C31*E31/IF(OR(D31="Kilo",D31="Litro"),1,IF(OR(D31="Gramos",D31="Mililitros"),1000,1)),0))) -> 0
E32: =IFERROR(_xlfn.XLOOKUP(B32,Ingredientes!B:B,Ingredientes!C:C),"") -> 0 | F32: =IF(E32="","",(ROUNDUP(C32*E32/IF(OR(D32="Kilo",D32="Litro"),1,IF(OR(D32="Gramos",D32="Mililitros"),1000,1)),0))) -> 0
B33: Costo de Receta | F33: =SUM(F9:F32) -> 522 | H33: Total Final | K33: =ROUNDUP(SUM(K24:K32),0) -> 120
F34: ⬆️ | K34: ⬆️
D35: Esto nos va a servir para continuar en el paso 2 | J35: Este es tu precio final de venta

Sheet Ingredientes
B2: Lista de Ingredientes
B3: Ingredientes | C3: Costo (por Kilo o Litro)
B4: Chile morita | C4: 200
B5: Chile guajillo | C5: 280
B6: Chile pasilla | C6: 339
B7: Chile arbol | C7: 108.5
B8: Ajo | C8: 140
B9: Nuez de la india | C9: 339
B10: Pistache | C10: 799
B11: Arandano | C11: 133
B12: Nuez garapiñada | C12: 450
B13: Avellana | C13: 600
B14: Aceite | C14: 37
B15: Ajonjoli | C15: 130
... B17: Sal | C17: 75
